{
	"bookmarkDisplayMode": 1,
	"lists": {
		"ADS-B": {
			"bookmarks": {
				"1090": {
					"bandwidth": 2000000.0,
					"frequency": 1090000000.0,
					"mode": 1
				}
			},
			"showOnWaterfall": true
		},
		"AIR": {
			"bookmarks": {
				"ZSHC:AP01": {
					"bandwidth": 10000.0,
					"frequency": 120050000.0,
					"mode": 2
				},
				"ZSHC:AP02": {
					"bandwidth": 10000.0,
					"frequency": 125550000.0,
					"mode": 2
				},
				"ZSHC:AP03": {
					"bandwidth": 10000.0,
					"frequency": 126050000.0,
					"mode": 2
				},
				"ZSHC:AP04": {
					"bandwidth": 10000.0,
					"frequency": 120400000.0,
					"mode": 2
				},
				"ZSHC:AP05": {
					"bandwidth": 10000.0,
					"frequency": 119425000.0,
					"mode": 2
				},
				"ZSHC:ATIS": {
					"bandwidth": 10000.0,
					"frequency": 127250000.0,
					"mode": 2
				},
				"ZSNB:AP01": {
					"bandwidth": 10000.0,
					"frequency": 125450000.0,
					"mode": 2
				},
				"ZSNB:AP02": {
					"bandwidth": 10000.0,
					"frequency": 119825000.0,
					"mode": 2
				},
				"ZSNB:ATIS": {
					"bandwidth": 10000.0,
					"frequency": 126450000.0,
					"mode": 2
				},
				"ZSPD:AP12": {
					"bandwidth": 10000.0,
					"frequency": 119975000.0,
					"mode": 2
				},
				"ZSPD:AR01": {
					"bandwidth": 10000.0,
					"frequency": 128325000.0,
					"mode": 2
				},
				"ZSPD:AR02": {
					"bandwidth": 10000.0,
					"frequency": 128750000.0,
					"mode": 2
				},
				"ZSPD:AR03": {
					"bandwidth": 10000.0,
					"frequency": 120950000.0,
					"mode": 2
				},
				"ZSPD:AR18": {
					"bandwidth": 10000.0,
					"frequency": 132625000.0,
					"mode": 2
				},
				"ZSPD:AR19": {
					"bandwidth": 10000.0,
					"frequency": 124950000.0,
					"mode": 2
				},
				"ZSPD:AR21": {
					"bandwidth": 10000.0,
					"frequency": 120700000.0,
					"mode": 2
				}
			},
			"showOnWaterfall": true
		},
		"APT": {
			"bookmarks": {
				"NOAA 15": {
					"bandwidth": 40000.0,
					"frequency": 137620000.0,
					"mode": 1
				},
				"NOAA 18": {
					"bandwidth": 40000.0,
					"frequency": 137912500.0,
					"mode": 1
				},
				"NOAA 19": {
					"bandwidth": 40000.0,
					"frequency": 137100000.0,
					"mode": 1
				}
			},
			"showOnWaterfall": true
		},
		"FM": {
			"bookmarks": {
				"FM 88.4": {
					"bandwidth": 200000.0,
					"frequency": 88400000.0,
					"mode": 1
				},
				"FM 89.8": {
					"bandwidth": 200000.0,
					"frequency": 89800000.0,
					"mode": 1
				},
				"FM 93.0": {
					"bandwidth": 200000.0,
					"frequency": 93000000.0,
					"mode": 1
				},
				"FM 95.7": {
					"bandwidth": 200000.0,
					"frequency": 95700000.0,
					"mode": 1
				},
				"FM 99.4": {
					"bandwidth": 200000.0,
					"frequency": 99400000.0,
					"mode": 1
				}
			},
			"showOnWaterfall": true
		},
		"HAM": {
			"bookmarks": {
				"14.270": {
					"bandwidth": 3000.0,
					"frequency": 14270000.0,
					"mode": 4
				},
				"7.050": {
					"bandwidth": 3000.0,
					"frequency": 7050000.0,
					"mode": 6
				}
			},
			"showOnWaterfall": true
		},
		"SW": {
			"bookmarks": {
				"5M": {
					"bandwidth": 10000.0,
					"frequency": 5000000.0,
					"mode": 2
				},
				"6M": {
					"bandwidth": 10000.0,
					"frequency": 6000000.0,
					"mode": 2
				},
				"7M": {
					"bandwidth": 10000.0,
					"frequency": 7000000.0,
					"mode": 2
				}
			},
			"showOnWaterfall": true
		}
	},
	"selectedList": "FM"
}
